prefig/__init__.py
prefig/cli.py
prefig/core/CTM.py
prefig/core/__init__.py
prefig/core/annotations.py
prefig/core/area.py
prefig/core/arrow.py
prefig/core/axes.py
prefig/core/calculus.py
prefig/core/circle.py
prefig/core/clip.py
prefig/core/compat.py
prefig/core/coordinates.py
prefig/core/definition.py
prefig/core/diagram.py
prefig/core/diffeqs.py
prefig/core/graph.py
prefig/core/grid_axes.py
prefig/core/group.py
prefig/core/image.py
prefig/core/implicit.py
prefig/core/label.py
prefig/core/label_tools.py
prefig/core/legend.py
prefig/core/line.py
prefig/core/math_utilities.py
prefig/core/network.py
prefig/core/parametric_curve.py
prefig/core/parse.py
prefig/core/path.py
prefig/core/point.py
prefig/core/polygon.py
prefig/core/read.py
prefig/core/rectangle.py
prefig/core/repeat.py
prefig/core/riemann_sum.py
prefig/core/shape.py
prefig/core/slope_field.py
prefig/core/statistics.py
prefig/core/tags.py
prefig/core/tangent_line.py
prefig/core/user_namespace.py
prefig/core/utilities.py
prefig/core/vector.py
prefig/engine.py
prefig/resources/diagcess/diagcess.html
prefig/resources/diagcess/diagcess.js
prefig/resources/examples/de-system.xml
prefig/resources/examples/derivatives.xml
prefig/resources/examples/diffeqs.xml
prefig/resources/examples/implicit.xml
prefig/resources/examples/projection.xml
prefig/resources/examples/riemann.xml
prefig/resources/examples/roots_of_unity.xml
prefig/resources/examples/tangent.xml
prefig/resources/fonts/Braille29.ttf
prefig/resources/js/mj-sre-page.js
prefig/resources/js/package.json
prefig/resources/schema/pf_schema.rnc
prefig/resources/schema/pf_schema.rng
prefig/resources/template/pf_publication.xml
prefig/scripts/__init__.py
prefig/scripts/install_mj.py
prefig-0.5.2.dist-info/LICENSE
prefig-0.5.2.dist-info/METADATA
prefig-0.5.2.dist-info/WHEEL
prefig-0.5.2.dist-info/entry_points.txt
prefig-0.5.2.dist-info/RECORD
