Metadata-Version: 2.1
Name: prefig
Version: 0.5.2
Summary: An authoring system for mathematical diagrams
Home-page: https://prefigure.org
License: GPL-3.0-or-later
Author: David Austin
Author-email: david.austin.m@gmail.com
Requires-Python: >=3.10,<4.0
Classifier: License :: OSI Approved :: GNU General Public License v3 or later (GPLv3+)
Classifier: Programming Language :: Python :: 3
Classifier: Programming Language :: Python :: 3.10
Classifier: Programming Language :: Python :: 3.11
Classifier: Programming Language :: Python :: 3.12
Provides-Extra: text
Requires-Dist: click (>=8.1.7,<9.0.0)
Requires-Dist: click-log (>=0.4.0,<0.5.0)
Requires-Dist: lxml (>=6,<7)
Requires-Dist: networkx (>=2.5,<3.0)
Requires-Dist: numpy (>=1.26,<2.0) ; python_version < "3.13"
Requires-Dist: numpy (>=2.1.0,<3.0.0) ; python_version >= "3.13"
Requires-Dist: pycairo (>=1.20,<2.0) ; extra == "text"
Requires-Dist: scipy (>=1.14.1,<2.0.0) ; python_version >= "3.13"
Requires-Dist: scipy (>=1.8,<2.0) ; python_version < "3.13"
Requires-Dist: shapely (>=2.0.6,<3.0.0)
Project-URL: Repository, https://github.com/davidaustinm/prefigure
